<?xml version="1.0" encoding="UTF-8"?>
<cppdepend-plugin tool="Misra">
<file path="c:\users\dell\desktop\antras kursas\antras semestras\t120m013 programų priežiūra ir tobulinimas\cppdepend2024.1\defaulttoolchain\include\string.h"><violation beginline="73" begincolumn="1" rule="Rule7-5-4" ruleset="Declarations">
</violation>
</file><file path="c:\users\dell\desktop\antras kursas\antras semestras\t120m013 programų priežiūra ir tobulinimas\laboratorinis1\dlib-19.24.2\dlib\unicode\unicode.cpp"><violation beginline="15" begincolumn="9" rule="Rule7-3-4" ruleset="Declarations">
</violation>
<violation beginline="25" begincolumn="5" rule="Rule11-0-1" ruleset="Classes">
</violation>
<violation beginline="33" begincolumn="17" rule="Rule6-4-1" ruleset="Statements">
</violation>
<violation beginline="33" begincolumn="17" rule="Rule6-4-1" ruleset="Statements">
</violation>
<violation beginline="36" begincolumn="20" rule="Rule18-4-1" ruleset="Library">
</violation>
<violation beginline="62" begincolumn="5" rule="Rule11-0-1" ruleset="Classes">
</violation>
<violation beginline="108" begincolumn="9" rule="Rule7-3-4" ruleset="Declarations">
</violation>
</file><file path="c:\users\dell\desktop\antras kursas\antras semestras\t120m013 programų priežiūra ir tobulinimas\laboratorinis1\dlib-19.24.2\dlib\unicode\unicode.h"><violation beginline="50" begincolumn="13" rule="Rule6-4-1" ruleset="Statements">
</violation>
<violation beginline="60" begincolumn="17" rule="Rule6-6-5" ruleset="Statements">
</violation>
<violation beginline="69" begincolumn="17" rule="Rule6-4-1" ruleset="Statements">
</violation>
<violation beginline="74" begincolumn="17" rule="Rule6-4-1" ruleset="Statements">
</violation>
<violation beginline="76" begincolumn="17" rule="Rule6-4-1" ruleset="Statements">
</violation>
<violation beginline="87" begincolumn="21" rule="Rule6-4-1" ruleset="Statements">
</violation>
<violation beginline="91" begincolumn="21" rule="Rule6-4-1" ruleset="Statements">
</violation>
<violation beginline="97" begincolumn="17" rule="Rule6-4-1" ruleset="Statements">
</violation>
<violation beginline="99" begincolumn="17" rule="Rule6-4-1" ruleset="Statements">
</violation>
<violation beginline="101" begincolumn="17" rule="Rule6-4-1" ruleset="Statements">
</violation>
<violation beginline="103" begincolumn="17" rule="Rule6-4-1" ruleset="Statements">
</violation>
<violation beginline="111" begincolumn="21" rule="Rule6-4-1" ruleset="Statements">
</violation>
<violation beginline="115" begincolumn="21" rule="Rule6-4-1" ruleset="Statements">
</violation>
<violation beginline="119" begincolumn="17" rule="Rule6-4-1" ruleset="Statements">
</violation>
<violation beginline="123" begincolumn="17" rule="Rule6-4-1" ruleset="Statements">
</violation>
<violation beginline="125" begincolumn="17" rule="Rule6-4-1" ruleset="Statements">
</violation>
<violation beginline="191" begincolumn="21" rule="Rule6-6-5" ruleset="Statements">
</violation>
<violation beginline="226" begincolumn="13" rule="Rule6-4-1" ruleset="Statements">
</violation>
<violation beginline="228" begincolumn="13" rule="Rule6-4-1" ruleset="Statements">
</violation>
<violation beginline="229" begincolumn="17" rule="Rule6-6-5" ruleset="Statements">
</violation>
<violation beginline="231" begincolumn="17" rule="Rule6-4-1" ruleset="Statements">
</violation>
<violation beginline="233" begincolumn="17" rule="Rule6-4-1" ruleset="Statements">
</violation>
<violation beginline="235" begincolumn="17" rule="Rule6-4-1" ruleset="Statements">
</violation>
<violation beginline="238" begincolumn="21" rule="Rule6-4-1" ruleset="Statements">
</violation>
<violation beginline="240" begincolumn="21" rule="Rule6-4-1" ruleset="Statements">
</violation>
<violation beginline="242" begincolumn="21" rule="Rule6-4-1" ruleset="Statements">
</violation>
<violation beginline="246" begincolumn="17" rule="Rule6-4-1" ruleset="Statements">
</violation>
<violation beginline="248" begincolumn="17" rule="Rule6-4-1" ruleset="Statements">
</violation>
<violation beginline="250" begincolumn="17" rule="Rule6-4-1" ruleset="Statements">
</violation>
<violation beginline="252" begincolumn="17" rule="Rule6-4-1" ruleset="Statements">
</violation>
<violation beginline="254" begincolumn="17" rule="Rule6-4-1" ruleset="Statements">
</violation>
<violation beginline="256" begincolumn="17" rule="Rule6-4-1" ruleset="Statements">
</violation>
<violation beginline="259" begincolumn="21" rule="Rule6-4-1" ruleset="Statements">
</violation>
<violation beginline="261" begincolumn="21" rule="Rule6-4-1" ruleset="Statements">
</violation>
<violation beginline="263" begincolumn="21" rule="Rule6-4-1" ruleset="Statements">
</violation>
<violation beginline="265" begincolumn="21" rule="Rule6-4-1" ruleset="Statements">
</violation>
<violation beginline="269" begincolumn="17" rule="Rule6-4-1" ruleset="Statements">
</violation>
<violation beginline="271" begincolumn="17" rule="Rule6-4-1" ruleset="Statements">
</violation>
<violation beginline="273" begincolumn="17" rule="Rule6-4-1" ruleset="Statements">
</violation>
<violation beginline="275" begincolumn="17" rule="Rule6-4-1" ruleset="Statements">
</violation>
<violation beginline="277" begincolumn="17" rule="Rule6-4-1" ruleset="Statements">
</violation>
<violation beginline="279" begincolumn="17" rule="Rule6-4-1" ruleset="Statements">
</violation>
<violation beginline="281" begincolumn="17" rule="Rule6-4-1" ruleset="Statements">
</violation>
<violation beginline="286" begincolumn="17" rule="Rule6-4-1" ruleset="Statements">
</violation>
<violation beginline="288" begincolumn="17" rule="Rule6-4-1" ruleset="Statements">
</violation>
<violation beginline="290" begincolumn="17" rule="Rule6-4-1" ruleset="Statements">
</violation>
<violation beginline="293" begincolumn="21" rule="Rule6-4-1" ruleset="Statements">
</violation>
<violation beginline="295" begincolumn="21" rule="Rule6-4-1" ruleset="Statements">
</violation>
<violation beginline="299" begincolumn="17" rule="Rule6-4-1" ruleset="Statements">
</violation>
<violation beginline="301" begincolumn="17" rule="Rule6-4-1" ruleset="Statements">
</violation>
<violation beginline="303" begincolumn="17" rule="Rule6-4-1" ruleset="Statements">
</violation>
<violation beginline="305" begincolumn="17" rule="Rule6-4-1" ruleset="Statements">
</violation>
<violation beginline="307" begincolumn="17" rule="Rule6-4-1" ruleset="Statements">
</violation>
<violation beginline="310" begincolumn="21" rule="Rule6-4-1" ruleset="Statements">
</violation>
<violation beginline="312" begincolumn="21" rule="Rule6-4-1" ruleset="Statements">
</violation>
<violation beginline="316" begincolumn="17" rule="Rule6-4-1" ruleset="Statements">
</violation>
<violation beginline="318" begincolumn="17" rule="Rule6-4-1" ruleset="Statements">
</violation>
<violation beginline="323" begincolumn="17" rule="Rule6-4-1" ruleset="Statements">
</violation>
<violation beginline="325" begincolumn="17" rule="Rule6-4-1" ruleset="Statements">
</violation>
<violation beginline="327" begincolumn="17" rule="Rule6-4-1" ruleset="Statements">
</violation>
<violation beginline="329" begincolumn="17" rule="Rule6-4-1" ruleset="Statements">
</violation>
<violation beginline="331" begincolumn="17" rule="Rule6-4-1" ruleset="Statements">
</violation>
<violation beginline="333" begincolumn="17" rule="Rule6-4-1" ruleset="Statements">
</violation>
<violation beginline="335" begincolumn="17" rule="Rule6-4-1" ruleset="Statements">
</violation>
<violation beginline="337" begincolumn="17" rule="Rule6-4-1" ruleset="Statements">
</violation>
<violation beginline="339" begincolumn="17" rule="Rule6-4-1" ruleset="Statements">
</violation>
<violation beginline="342" begincolumn="21" rule="Rule6-4-1" ruleset="Statements">
</violation>
<violation beginline="346" begincolumn="17" rule="Rule6-4-1" ruleset="Statements">
</violation>
<violation beginline="348" begincolumn="17" rule="Rule6-4-1" ruleset="Statements">
</violation>
<violation beginline="350" begincolumn="17" rule="Rule6-4-1" ruleset="Statements">
</violation>
<violation beginline="352" begincolumn="17" rule="Rule6-4-1" ruleset="Statements">
</violation>
<violation beginline="354" begincolumn="17" rule="Rule6-4-1" ruleset="Statements">
</violation>
<violation beginline="357" begincolumn="21" rule="Rule6-4-1" ruleset="Statements">
</violation>
<violation beginline="361" begincolumn="17" rule="Rule6-4-1" ruleset="Statements">
</violation>
<violation beginline="363" begincolumn="17" rule="Rule6-4-1" ruleset="Statements">
</violation>
<violation beginline="365" begincolumn="17" rule="Rule6-4-1" ruleset="Statements">
</violation>
<violation beginline="367" begincolumn="17" rule="Rule6-4-1" ruleset="Statements">
</violation>
<violation beginline="369" begincolumn="17" rule="Rule6-4-1" ruleset="Statements">
</violation>
<violation beginline="374" begincolumn="17" rule="Rule6-4-1" ruleset="Statements">
</violation>
<violation beginline="376" begincolumn="17" rule="Rule6-4-1" ruleset="Statements">
</violation>
<violation beginline="378" begincolumn="17" rule="Rule6-4-1" ruleset="Statements">
</violation>
<violation beginline="380" begincolumn="17" rule="Rule6-4-1" ruleset="Statements">
</violation>
<violation beginline="382" begincolumn="17" rule="Rule6-4-1" ruleset="Statements">
</violation>
<violation beginline="384" begincolumn="17" rule="Rule6-4-1" ruleset="Statements">
</violation>
<violation beginline="386" begincolumn="17" rule="Rule6-4-1" ruleset="Statements">
</violation>
<violation beginline="389" begincolumn="21" rule="Rule6-4-1" ruleset="Statements">
</violation>
<violation beginline="393" begincolumn="17" rule="Rule6-4-1" ruleset="Statements">
</violation>
<violation beginline="395" begincolumn="17" rule="Rule6-4-1" ruleset="Statements">
</violation>
<violation beginline="397" begincolumn="17" rule="Rule6-4-1" ruleset="Statements">
</violation>
<violation beginline="399" begincolumn="17" rule="Rule6-4-1" ruleset="Statements">
</violation>
<violation beginline="401" begincolumn="17" rule="Rule6-4-1" ruleset="Statements">
</violation>
<violation beginline="403" begincolumn="17" rule="Rule6-4-1" ruleset="Statements">
</violation>
<violation beginline="405" begincolumn="17" rule="Rule6-4-1" ruleset="Statements">
</violation>
<violation beginline="407" begincolumn="17" rule="Rule6-4-1" ruleset="Statements">
</violation>
<violation beginline="409" begincolumn="17" rule="Rule6-4-1" ruleset="Statements">
</violation>
<violation beginline="411" begincolumn="17" rule="Rule6-4-1" ruleset="Statements">
</violation>
<violation beginline="416" begincolumn="17" rule="Rule6-4-1" ruleset="Statements">
</violation>
<violation beginline="418" begincolumn="17" rule="Rule6-4-1" ruleset="Statements">
</violation>
<violation beginline="420" begincolumn="17" rule="Rule6-4-1" ruleset="Statements">
</violation>
<violation beginline="422" begincolumn="17" rule="Rule6-4-1" ruleset="Statements">
</violation>
<violation beginline="424" begincolumn="17" rule="Rule6-4-1" ruleset="Statements">
</violation>
<violation beginline="426" begincolumn="17" rule="Rule6-4-1" ruleset="Statements">
</violation>
<violation beginline="428" begincolumn="17" rule="Rule6-4-1" ruleset="Statements">
</violation>
<violation beginline="430" begincolumn="17" rule="Rule6-4-1" ruleset="Statements">
</violation>
<violation beginline="432" begincolumn="17" rule="Rule6-4-1" ruleset="Statements">
</violation>
<violation beginline="434" begincolumn="17" rule="Rule6-4-1" ruleset="Statements">
</violation>
<violation beginline="436" begincolumn="17" rule="Rule6-4-1" ruleset="Statements">
</violation>
<violation beginline="438" begincolumn="17" rule="Rule6-4-1" ruleset="Statements">
</violation>
<violation beginline="440" begincolumn="17" rule="Rule6-4-1" ruleset="Statements">
</violation>
<violation beginline="442" begincolumn="17" rule="Rule6-4-1" ruleset="Statements">
</violation>
<violation beginline="444" begincolumn="17" rule="Rule6-4-1" ruleset="Statements">
</violation>
<violation beginline="446" begincolumn="17" rule="Rule6-4-1" ruleset="Statements">
</violation>
<violation beginline="448" begincolumn="17" rule="Rule6-4-1" ruleset="Statements">
</violation>
<violation beginline="450" begincolumn="17" rule="Rule6-4-1" ruleset="Statements">
</violation>
<violation beginline="453" begincolumn="21" rule="Rule6-4-1" ruleset="Statements">
</violation>
<violation beginline="457" begincolumn="17" rule="Rule6-4-1" ruleset="Statements">
</violation>
<violation beginline="459" begincolumn="17" rule="Rule6-4-1" ruleset="Statements">
</violation>
<violation beginline="461" begincolumn="17" rule="Rule6-4-1" ruleset="Statements">
</violation>
<violation beginline="466" begincolumn="17" rule="Rule6-4-1" ruleset="Statements">
</violation>
<violation beginline="468" begincolumn="17" rule="Rule6-4-1" ruleset="Statements">
</violation>
<violation beginline="470" begincolumn="17" rule="Rule6-4-1" ruleset="Statements">
</violation>
<violation beginline="472" begincolumn="17" rule="Rule6-4-1" ruleset="Statements">
</violation>
<violation beginline="474" begincolumn="17" rule="Rule6-4-1" ruleset="Statements">
</violation>
<violation beginline="476" begincolumn="17" rule="Rule6-4-1" ruleset="Statements">
</violation>
<violation beginline="478" begincolumn="17" rule="Rule6-4-1" ruleset="Statements">
</violation>
<violation beginline="480" begincolumn="17" rule="Rule6-4-1" ruleset="Statements">
</violation>
<violation beginline="482" begincolumn="17" rule="Rule6-4-1" ruleset="Statements">
</violation>
<violation beginline="484" begincolumn="17" rule="Rule6-4-1" ruleset="Statements">
</violation>
<violation beginline="486" begincolumn="17" rule="Rule6-4-1" ruleset="Statements">
</violation>
<violation beginline="488" begincolumn="17" rule="Rule6-4-1" ruleset="Statements">
</violation>
<violation beginline="490" begincolumn="17" rule="Rule6-4-1" ruleset="Statements">
</violation>
<violation beginline="492" begincolumn="17" rule="Rule6-4-1" ruleset="Statements">
</violation>
<violation beginline="494" begincolumn="17" rule="Rule6-4-1" ruleset="Statements">
</violation>
<violation beginline="496" begincolumn="17" rule="Rule6-4-1" ruleset="Statements">
</violation>
<violation beginline="501" begincolumn="17" rule="Rule6-4-1" ruleset="Statements">
</violation>
<violation beginline="503" begincolumn="17" rule="Rule6-4-1" ruleset="Statements">
</violation>
<violation beginline="505" begincolumn="17" rule="Rule6-4-1" ruleset="Statements">
</violation>
<violation beginline="507" begincolumn="17" rule="Rule6-4-1" ruleset="Statements">
</violation>
<violation beginline="509" begincolumn="17" rule="Rule6-4-1" ruleset="Statements">
</violation>
<violation beginline="511" begincolumn="17" rule="Rule6-4-1" ruleset="Statements">
</violation>
<violation beginline="513" begincolumn="17" rule="Rule6-4-1" ruleset="Statements">
</violation>
<violation beginline="515" begincolumn="17" rule="Rule6-4-1" ruleset="Statements">
</violation>
<violation beginline="517" begincolumn="17" rule="Rule6-4-1" ruleset="Statements">
</violation>
<violation beginline="519" begincolumn="17" rule="Rule6-4-1" ruleset="Statements">
</violation>
<violation beginline="521" begincolumn="17" rule="Rule6-4-1" ruleset="Statements">
</violation>
<violation beginline="523" begincolumn="17" rule="Rule6-4-1" ruleset="Statements">
</violation>
<violation beginline="525" begincolumn="17" rule="Rule6-4-1" ruleset="Statements">
</violation>
<violation beginline="527" begincolumn="17" rule="Rule6-4-1" ruleset="Statements">
</violation>
<violation beginline="529" begincolumn="17" rule="Rule6-4-1" ruleset="Statements">
</violation>
<violation beginline="531" begincolumn="17" rule="Rule6-4-1" ruleset="Statements">
</violation>
<violation beginline="533" begincolumn="17" rule="Rule6-4-1" ruleset="Statements">
</violation>
<violation beginline="535" begincolumn="17" rule="Rule6-4-1" ruleset="Statements">
</violation>
<violation beginline="537" begincolumn="17" rule="Rule6-4-1" ruleset="Statements">
</violation>
<violation beginline="541" begincolumn="13" rule="Rule6-4-1" ruleset="Statements">
</violation>
<violation beginline="543" begincolumn="13" rule="Rule6-4-1" ruleset="Statements">
</violation>
<violation beginline="545" begincolumn="13" rule="Rule6-4-1" ruleset="Statements">
</violation>
<violation beginline="547" begincolumn="13" rule="Rule6-4-1" ruleset="Statements">
</violation>
<violation beginline="549" begincolumn="13" rule="Rule6-4-1" ruleset="Statements">
</violation>
<violation beginline="551" begincolumn="13" rule="Rule6-4-1" ruleset="Statements">
</violation>
<violation beginline="553" begincolumn="13" rule="Rule6-4-1" ruleset="Statements">
</violation>
<violation beginline="555" begincolumn="13" rule="Rule6-4-1" ruleset="Statements">
</violation>
<violation beginline="557" begincolumn="13" rule="Rule6-4-1" ruleset="Statements">
</violation>
<violation beginline="559" begincolumn="13" rule="Rule6-4-1" ruleset="Statements">
</violation>
<violation beginline="561" begincolumn="13" rule="Rule6-4-1" ruleset="Statements">
</violation>
<violation beginline="563" begincolumn="13" rule="Rule6-4-1" ruleset="Statements">
</violation>
<violation beginline="565" begincolumn="13" rule="Rule6-4-1" ruleset="Statements">
</violation>
<violation beginline="567" begincolumn="13" rule="Rule6-4-1" ruleset="Statements">
</violation>
<violation beginline="569" begincolumn="13" rule="Rule6-4-1" ruleset="Statements">
</violation>
<violation beginline="571" begincolumn="13" rule="Rule6-4-1" ruleset="Statements">
</violation>
<violation beginline="573" begincolumn="13" rule="Rule6-4-1" ruleset="Statements">
</violation>
<violation beginline="575" begincolumn="13" rule="Rule6-4-1" ruleset="Statements">
</violation>
<violation beginline="577" begincolumn="13" rule="Rule6-4-1" ruleset="Statements">
</violation>
<violation beginline="579" begincolumn="13" rule="Rule6-4-1" ruleset="Statements">
</violation>
<violation beginline="581" begincolumn="13" rule="Rule6-4-1" ruleset="Statements">
</violation>
<violation beginline="583" begincolumn="13" rule="Rule6-4-1" ruleset="Statements">
</violation>
<violation beginline="585" begincolumn="13" rule="Rule6-4-1" ruleset="Statements">
</violation>
<violation beginline="587" begincolumn="13" rule="Rule6-4-1" ruleset="Statements">
</violation>
<violation beginline="589" begincolumn="13" rule="Rule6-4-1" ruleset="Statements">
</violation>
<violation beginline="591" begincolumn="13" rule="Rule6-4-1" ruleset="Statements">
</violation>
<violation beginline="593" begincolumn="13" rule="Rule6-4-1" ruleset="Statements">
</violation>
<violation beginline="595" begincolumn="13" rule="Rule6-4-1" ruleset="Statements">
</violation>
<violation beginline="597" begincolumn="13" rule="Rule6-4-1" ruleset="Statements">
</violation>
<violation beginline="599" begincolumn="13" rule="Rule6-4-1" ruleset="Statements">
</violation>
<violation beginline="601" begincolumn="13" rule="Rule6-4-1" ruleset="Statements">
</violation>
<violation beginline="603" begincolumn="13" rule="Rule6-4-1" ruleset="Statements">
</violation>
<violation beginline="605" begincolumn="13" rule="Rule6-4-1" ruleset="Statements">
</violation>
<violation beginline="607" begincolumn="13" rule="Rule6-4-1" ruleset="Statements">
</violation>
<violation beginline="620" begincolumn="9" rule="Rule7-3-4" ruleset="Declarations">
</violation>
<violation beginline="622" begincolumn="17" rule="Rule5-14-1" ruleset="Statements">
</violation>
<violation beginline="629" begincolumn="9" rule="Rule7-3-4" ruleset="Declarations">
</violation>
<violation beginline="659" begincolumn="13" rule="Rule6-3-1" ruleset="Statements">
</violation>
<violation beginline="669" begincolumn="17" rule="Rule6-3-1" ruleset="Statements">
</violation>
<violation beginline="671" begincolumn="17" rule="Rule6-6-5" ruleset="Statements">
</violation>
<violation beginline="712" begincolumn="13" rule="Rule6-4-1" ruleset="Statements">
</violation>
</file></cppdepend-plugin>